mpwf/__init__.py
mpwf/api.py
mpwf/middleware.py
mpwf/response.py
mpwf-0.0.3.dist-info/METADATA
mpwf-0.0.3.dist-info/WHEEL
mpwf-0.0.3.dist-info/top_level.txt
mpwf-0.0.3.dist-info/RECORD
