Metadata-Version: 2.1
Name: mpwf
Version: 0.0.3
Summary: My Pyhton Web Framework, Based on the testdriven.io tutorial "Building your own Python web framework".
Home-page: UNKNOWN
Author: Renaud Cepre
Author-email: renaudcepre@gmail.com
License: MIT
Platform: UNKNOWN
Classifier: Programming Language :: Python :: 3.6
Requires-Python: >=3.6.0
Requires-Dist: Jinja2 (==2.11.2)
Requires-Dist: WebOb (==1.8.6)
Requires-Dist: gunicorn (==20.0.4)
Requires-Dist: parse (==1.17.0)
Requires-Dist: requests-wsgi-adapter (==0.4.1)
Requires-Dist: requests (==2.24.0)
Requires-Dist: whitenoise (==5.2.0)
